{
  "version": "1.0.0",
  "generator": "brikc_cli_l6plus route2 bounded emitter",
  "issuer": "BRIK-64 L6+ internal non-claim",
  "engine": "l6_plus",
  "engine_tier": "internal_generation",
  "lane": "internal_adaptive",
  "claim_authority": "non_claim",
  "public_claim_allowed": false,
  "numeric_domain": {
    "schema_version": "brik64.numeric_domain_engine_output.v1",
    "engine_id": "l6_plus",
    "engine_tier": "internal_generation",
    "claim_authority": "internal_non_claim",
    "certifies_tests": false,
    "analysis_status": "parsed",
    "profile_required": false,
    "numeric_domain_profile_hashes": [],
    "validation_issues": [],
    "guard_stability_findings": [],
    "backend_profile_required_for_strong_certification": true
  },
  "source": {
    "pc": "brik_cli_beta9_transpiler_contract",
    "function": "brik_cli_beta9_transpiler_contract",
    "hash_sha256": "ee186452a7a857fcd3ea643126ce90541bcdfb13044ec2385dcddbe0367455db",
    "language": "pcd"
  },
  "certification": {
    "level": "ROUTE2_BOUNDED_INTERNAL",
    "domain_safe": true,
    "deterministic": true,
    "total_statements": 22,
    "certifies_full_repository": false
  },
  "target": {
    "language": "js",
    "file": "brik_cli_beta9_transpiler_contract.js",
    "hash_sha256": "fe5eb705b004fc3c0c3b0765404235da2596f2fc5ec1b8f8dfb0fc6146786fd9"
  },
  "non_claims": [
    "does not certify full repository correctness",
    "does not certify external source authority",
    "does not certify security or deployment behavior",
    "does not certify future changes"
  ]
}