{
  "schemaVersion": "brik64.release_train_live_verify_report.v1",
  "releaseId": "brik64-0.1.0-beta.10",
  "version": "0.1.0-beta.10",
  "manifestDigest": "b29b12cc2674138f14385554993dedb426acdbdc5fa40e3de84ce437e3024852",
  "attempt": 1,
  "maxAttempts": 31,
  "decision": "PASS_RELEASE_TRAIN_LIVE_VERIFY",
  "publicationAllowed": false,
  "boundary": "Live verification only. This report observes public surfaces and does not mutate or publish.",
  "observations": [
    {
      "id": "curl_installer",
      "url": "https://brik64.com/cli/install.sh",
      "statusCode": 200,
      "transport": "curl",
      "sha256": "13f137ce7a3821d55989580e88d1aac778060365a90df9feca8a7ed54f310c1a",
      "bytes": 3052
    },
    {
      "id": "channel_manifest",
      "url": "https://brik64.com/cli/beta.json",
      "statusCode": 200,
      "transport": "curl",
      "sha256": "d8f3c981e291bf6c8adeb73d81af481981e56d659ea9605b28579b04e75bb7fe",
      "bytes": 358
    },
    {
      "id": "github_release",
      "url": "https://github.com/brik64/brik64-cli/releases/tag/v0.1.0-beta.10",
      "statusCode": 200,
      "transport": "curl",
      "sha256": "89b79d942580db5136b83d9331a6668972d94a440906511f20a675abc71dd610",
      "bytes": 219808
    },
    {
      "id": "docs_install",
      "url": "https://docs.brik64.com/cli/install.md",
      "statusCode": 200,
      "transport": "curl",
      "sha256": "44461097cbcfe159526216ecb4961ce958711c37ca595a776db01f62dab6d299",
      "bytes": 3040
    },
    {
      "id": "web_home",
      "url": "https://brik64.com/",
      "statusCode": 200,
      "transport": "curl",
      "sha256": "cd52f10e8b0bc20554a47a0456633f2996fa6ecb2dc1fae8fe516960c07450a2",
      "bytes": 304137
    },
    {
      "id": "web_changelog",
      "url": "https://brik64.com/changelog",
      "statusCode": 200,
      "transport": "curl",
      "sha256": "d937844f8c6142ffe0f66886112370cf75640d346c58d04329b3a636f991e7c5",
      "bytes": 77908
    },
    {
      "id": "npm_sdk",
      "url": "https://registry.npmjs.org/@brik64%2Fcore",
      "statusCode": 200,
      "transport": "curl",
      "sha256": "3145bf46a1f0389a079e2e24bd2ee1a45b8e7ea3a677293480b81f3c5769feb4",
      "bytes": 17667
    },
    {
      "id": "pypi_sdk",
      "url": "https://pypi.org/pypi/brik64/0.1.0b10/json",
      "statusCode": 200,
      "transport": "curl",
      "sha256": "37cd7b78a6bbf86bff2eae97aa6fc5ac02ba5684eb50f21804de031886ddc0a3",
      "bytes": 4196
    },
    {
      "id": "crates_sdk",
      "url": "https://crates.io/api/v1/crates/brik64-core",
      "statusCode": 200,
      "transport": "curl",
      "sha256": "7619dc75616508c0bceb065a8f01117ae7bdeb34712ee21191c2da443bf33dae",
      "bytes": 23172
    },
    {
      "id": "public_skill",
      "url": "https://raw.githubusercontent.com/brik64/brik64-tools-skills/main/skills/brik64/SKILL.md",
      "statusCode": 200,
      "transport": "curl",
      "sha256": "979222963989a9ce1ab8dc17a18a2b660d0ca86d549c84ad7b92932b3443775c",
      "bytes": 7980
    }
  ],
  "failures": []
}
